lp_monitor/__init__.py
lp_monitor/cli.py
lp_monitor/lp_monitor.py
lp_monitor/rpc.py
lp_monitor-0.4.1.dist-info/DESCRIPTION.rst
lp_monitor-0.4.1.dist-info/METADATA
lp_monitor-0.4.1.dist-info/RECORD
lp_monitor-0.4.1.dist-info/WHEEL
lp_monitor-0.4.1.dist-info/entry_points.txt
lp_monitor-0.4.1.dist-info/metadata.json
lp_monitor-0.4.1.dist-info/top_level.txt
