Metadata-Version: 2.0
Name: lp-monitor
Version: 0.4.1
Summary: A Liquidity Provider Node monitoring facility
Home-page: https://github.com/askz/lp_monitor
Author: Maxime Saddok
Author-email: maxime@monaize.com
License: GNU Lesser General Public License v3
Keywords: lp_monitor
Platform: UNKNOWN
Classifier: Development Status :: 2 - Pre-Alpha
Classifier: Intended Audience :: Developers
Classifier: License :: OSI Approved :: GNU General Public License v3 (GPLv3)
Classifier: Natural Language :: English
Classifier: Programming Language :: Python :: 2
Classifier: Programming Language :: Python :: 2.6
Classifier: Programming Language :: Python :: 2.7
Classifier: Programming Language :: Python :: 3
Classifier: Programming Language :: Python :: 3.3
Classifier: Programming Language :: Python :: 3.4
Classifier: Programming Language :: Python :: 3.5
Requires-Dist: Click (>=6.0)
Requires-Dist: python-bitcoinlib (==0.9.0)
